aalink.cpython-312-aarch64-linux-gnu.so
aalink.libs/libatomic-3eb8c8ee.so.1.2.0
aalink-0.1.1.dist-info/METADATA
aalink-0.1.1.dist-info/WHEEL
aalink-0.1.1.dist-info/RECORD
aalink-0.1.1.dist-info/licenses/LICENSE
