Metadata-Version: 2.2
Name: aalink
Version: 0.1.1
Summary: Async Python interface for Ableton Link
Author-Email: Artem Popov <art@artfwo.net>
Classifier: Development Status :: 4 - Beta
Classifier: Intended Audience :: Developers
Classifier: License :: OSI Approved :: GNU General Public License v3 or later (GPLv3+)
Classifier: Programming Language :: Python :: 3
Classifier: Topic :: Artistic Software
Classifier: Topic :: Multimedia :: Sound/Audio
Classifier: Topic :: Software Development :: Libraries
Classifier: Topic :: System :: Networking
Project-URL: Homepage, https://github.com/artfwo/aalink
Requires-Python: >=3.9
